ninegagposts/__init__.py
ninegagposts/main.py
ninegagposts-0.0.1.5.dist-info/LICENSE
ninegagposts-0.0.1.5.dist-info/METADATA
ninegagposts-0.0.1.5.dist-info/WHEEL
ninegagposts-0.0.1.5.dist-info/top_level.txt
ninegagposts-0.0.1.5.dist-info/RECORD
