Metadata-Version: 2.1
Name: ninegagposts
Version: 0.0.1.5
Summary: UNKNOWN
Home-page: https://github.com/lucasqm/9gagclient
Author: Lucas Quintela
Author-email: lucas.qmiranda@gmail.com
License: License :: OSI Approved :: MIT License
Platform: UNKNOWN
Classifier: Programming Language :: Python
Classifier: Programming Language :: Python :: 3
Requires-Python: >=3.6
Requires-Dist: requests
